setup.py
bolacha/__init__.py
bolacha/meta.py
bolacha/multipart.py
bolacha.egg-info/PKG-INFO
bolacha.egg-info/SOURCES.txt
bolacha.egg-info/dependency_links.txt
bolacha.egg-info/requires.txt
bolacha.egg-info/top_level.txt