Metadata-Version: 1.0
Name: bolacha
Version: 0.2.2
Summary: Bolacha is a simple http client that allows you testing http requests, handling cookies and file upload.
Home-page: UNKNOWN
Author: Gabriel Falcão
Author-email: gabriel@nacaolivre.org
License: UNKNOWN
Platform: UNKNOWN
